[
  {
    "epoch": 0,
    "metrics": {
      "d_train_loss": {
        "train": 0.013780362921167764,
        "val": 0.013779925521958638
      },
      "d_fool_loss": {
        "train": 0.006832831055235274,
        "val": 0.006832832401719293
      },
      "recon_loss": {
        "train": 0.04132069056443349,
        "val": 0.0518154301153028
      },
      "psnr": {
        "train": 14.930413588745514,
        "val": 14.170219136131703
      },
      "ssim": {
        "train": 0.4199893508077604,
        "val": 0.4126806695401478
      }
    }
  },
  {
    "epoch": 1,
    "metrics": {
      "d_train_loss": {
        "train": 0.013483808703974566,
        "val": 0.013472201465514345
      },
      "d_fool_loss": {
        "train": 0.007528478247553136,
        "val": 0.007538886317579543
      },
      "recon_loss": {
        "train": 0.007918446840493698,
        "val": 0.008600789992817737
      },
      "psnr": {
        "train": 21.98185078613759,
        "val": 21.638775602650036
      },
      "ssim": {
        "train": 0.7247989724760329,
        "val": 0.7331974767296336
      }
    }
  },
  {
    "epoch": 2,
    "metrics": {
      "d_train_loss": {
        "train": 0.013689362011700087,
        "val": 0.013505507721634481
      },
      "d_fool_loss": {
        "train": 0.007204290028006958,
        "val": 0.007411489662315164
      },
      "recon_loss": {
        "train": 0.006534282541410489,
        "val": 0.006958654088431538
      },
      "psnr": {
        "train": 22.85971257592998,
        "val": 22.61992278765266
      },
      "ssim": {
        "train": 0.7497689356696935,
        "val": 0.7555864036478338
      }
    }
  },
  {
    "epoch": 3,
    "metrics": {
      "d_train_loss": {
        "train": 0.013931270709938624,
        "val": 0.013889211030410869
      },
      "d_fool_loss": {
        "train": 0.007049307696866458,
        "val": 0.00710092123088615
      },
      "recon_loss": {
        "train": 0.006168489631996458,
        "val": 0.006611443733741423
      },
      "psnr": {
        "train": 23.247458717454922,
        "val": 22.95318727926105
      },
      "ssim": {
        "train": 0.7595575989889427,
        "val": 0.7634193355313083
      }
    }
  },
  {
    "epoch": 4,
    "metrics": {
      "d_train_loss": {
        "train": 0.01368208180696189,
        "val": 0.01360295563385698
      },
      "d_fool_loss": {
        "train": 0.007186608577482533,
        "val": 0.007273467294321272
      },
      "recon_loss": {
        "train": 0.005567251571732527,
        "val": 0.0059403203103205035
      },
      "psnr": {
        "train": 23.752977088003306,
        "val": 23.527977756296114
      },
      "ssim": {
        "train": 0.7785658869229276,
        "val": 0.7840878470097014
      }
    }
  },
  {
    "epoch": 5,
    "metrics": {
      "d_train_loss": {
        "train": 0.013825939941363266,
        "val": 0.013823333687236157
      },
      "d_fool_loss": {
        "train": 0.007132038642600231,
        "val": 0.007148462757147078
      },
      "recon_loss": {
        "train": 0.006402200050863691,
        "val": 0.006918054022436291
      },
      "psnr": {
        "train": 23.156092174110093,
        "val": 22.838532340379846
      },
      "ssim": {
        "train": 0.7777373644268635,
        "val": 0.7831991901869972
      }
    }
  },
  {
    "epoch": 6,
    "metrics": {
      "d_train_loss": {
        "train": 0.013859375017708155,
        "val": 0.013775909218588485
      },
      "d_fool_loss": {
        "train": 0.007140739684944022,
        "val": 0.007233112215481955
      },
      "recon_loss": {
        "train": 0.006926952254342996,
        "val": 0.007252535116377062
      },
      "psnr": {
        "train": 22.486897274668845,
        "val": 22.33312912474845
      },
      "ssim": {
        "train": 0.7586929482941126,
        "val": 0.763871978678311
      }
    }
  },
  {
    "epoch": 7,
    "metrics": {
      "d_train_loss": {
        "train": 0.013905068213068,
        "val": 0.01387247737506267
      },
      "d_fool_loss": {
        "train": 0.0068403234130579174,
        "val": 0.006871296672077088
      },
      "recon_loss": {
        "train": 0.006295194163701947,
        "val": 0.006665315208360186
      },
      "psnr": {
        "train": 23.214583926782137,
        "val": 23.00332648338127
      },
      "ssim": {
        "train": 0.7736787278505931,
        "val": 0.780719742177579
      }
    }
  },
  {
    "epoch": 8,
    "metrics": {
      "d_train_loss": {
        "train": 0.01371750746970879,
        "val": 0.013671510864342816
      },
      "d_fool_loss": {
        "train": 0.007447486052979956,
        "val": 0.007494222410619626
      },
      "recon_loss": {
        "train": 0.005787967231451905,
        "val": 0.006263189333183645
      },
      "psnr": {
        "train": 23.522873007707734,
        "val": 23.21271684259167
      },
      "ssim": {
        "train": 0.7660625521378955,
        "val": 0.7681960713958341
      }
    }
  },
  {
    "epoch": 9,
    "metrics": {
      "d_train_loss": {
        "train": 0.014523259447920104,
        "val": 0.01446700448243709
      },
      "d_fool_loss": {
        "train": 0.006437265995557752,
        "val": 0.00647325652623962
      },
      "recon_loss": {
        "train": 0.0068495471732222014,
        "val": 0.007366947143847866
      },
      "psnr": {
        "train": 22.47254521245747,
        "val": 22.206893954309013
      },
      "ssim": {
        "train": 0.7541890954882287,
        "val": 0.7554740197336134
      }
    }
  },
  {
    "epoch": 10,
    "metrics": {
      "d_train_loss": {
        "train": 0.013827130942559846,
        "val": 0.01382812688108809
      },
      "d_fool_loss": {
        "train": 0.0069504080350849436,
        "val": 0.006951746837066238
      },
      "recon_loss": {
        "train": 0.005374696710793354,
        "val": 0.005693142048858583
      },
      "psnr": {
        "train": 23.824541943862794,
        "val": 23.681233279826973
      },
      "ssim": {
        "train": 0.7836756712862815,
        "val": 0.7891253727819927
      }
    }
  }
]