{
  "experiment_name": "exp_more_visualizations_v3/dmfa_comp_cnv",
  "max_benchmark_batches": -1,
  "render_every": 3,
  "dump_val_predictions": false,
  "dump_sample_results": true,
  "dataset": "mnist",
  "img_size": 28,
  "mask_hidden_h": 14,
  "mask_hidden_w": 14,
  "mask_unknown_size": -1,
  "batch_size": 24,
  "lr": 0.001,
  "num_epochs": 10,
  "device": "cuda:0",
  "dataset_root": "/mnt/users/mprzewiezlikowski/local/data/.data",
  "convar_type": "naive",
  "convar_append_mask": false,
  "seed": false,
  "train_inpainter_layer": false,
  "results_dir": "../results/classification",
  "inpainter_type": "dmfa",
  "inpainter_path": "../results/inpainting/mnist/complete_data/v1",
  "convar_channels": 32,
  "n_classes": 10
}