[
  {
    "epoch": 0,
    "metrics": {
      "mse": {
        "train": 41.32272319888594,
        "val": 40.82927265451915
      },
      "nll": {
        "train": -3709.326236250389,
        "val": -3698.144098841729
      },
      "objective": {
        "train": -3668.003506636738,
        "val": -3657.3148138701026
      }
    }
  },
  {
    "epoch": 3,
    "metrics": {
      "mse": {
        "train": 29.514528113218088,
        "val": 29.492640547491426
      },
      "nll": {
        "train": -4395.695740049751,
        "val": -4377.549736668221
      },
      "objective": {
        "train": -4366.181192426539,
        "val": -4348.05710582828
      }
    }
  },
  {
    "epoch": 6,
    "metrics": {
      "mse": {
        "train": 27.801029641829913,
        "val": 27.556760047798726
      },
      "nll": {
        "train": -4589.133835218439,
        "val": -4598.999140041978
      },
      "objective": {
        "train": -4561.332797681514,
        "val": -4571.442391314909
      }
    }
  },
  {
    "epoch": 9,
    "metrics": {
      "mse": {
        "train": 25.66197532919509,
        "val": 26.151936792022553
      },
      "nll": {
        "train": -4757.128779928483,
        "val": -4746.276358685091
      },
      "objective": {
        "train": -4757.128779928483,
        "val": -4746.276358685091
      }
    }
  },
  {
    "epoch": 12,
    "metrics": {
      "mse": {
        "train": 26.271290461222332,
        "val": 26.854209377991026
      },
      "nll": {
        "train": -4835.046335704291,
        "val": -4813.236784825871
      },
      "objective": {
        "train": -4835.046335704291,
        "val": -4813.236784825871
      }
    }
  },
  {
    "epoch": 15,
    "metrics": {
      "mse": {
        "train": 26.315478187295334,
        "val": 26.447640831790753
      },
      "nll": {
        "train": -4934.6436202775185,
        "val": -4907.276590679416
      },
      "objective": {
        "train": -4934.6436202775185,
        "val": -4907.276590679416
      }
    }
  },
  {
    "epoch": 18,
    "metrics": {
      "mse": {
        "train": 27.707232489514706,
        "val": 27.92102158959232
      },
      "nll": {
        "train": -4954.795798837842,
        "val": -4927.947860793688
      },
      "objective": {
        "train": -4954.795798837842,
        "val": -4927.947860793688
      }
    }
  },
  {
    "epoch": 21,
    "metrics": {
      "mse": {
        "train": 24.737182370465785,
        "val": 24.989821419787052
      },
      "nll": {
        "train": -4980.641543260262,
        "val": -4955.874985424441
      },
      "objective": {
        "train": -4980.641543260262,
        "val": -4955.874985424441
      }
    }
  },
  {
    "epoch": 24,
    "metrics": {
      "mse": {
        "train": 25.448308536662392,
        "val": 25.27894786815738
      },
      "nll": {
        "train": -5065.829184157338,
        "val": -5035.434550878421
      },
      "objective": {
        "train": -5065.829184157338,
        "val": -5035.434550878421
      }
    }
  },
  {
    "epoch": 27,
    "metrics": {
      "mse": {
        "train": 23.024416059996952,
        "val": 23.19940720268743
      },
      "nll": {
        "train": -5086.428672069341,
        "val": -5069.776544523476
      },
      "objective": {
        "train": -5086.428672069341,
        "val": -5069.776544523476
      }
    }
  },
  {
    "epoch": 28,
    "metrics": {
      "mse": {
        "train": 24.36812984409617,
        "val": 24.454056782508964
      },
      "nll": {
        "train": -5085.428839688278,
        "val": -5062.777761582712
      },
      "objective": {
        "train": -5085.428839688278,
        "val": -5062.777761582712
      }
    }
  },
  {
    "epoch": 28,
    "metrics": {
      "mse": {
        "train": 24.19495166000442,
        "val": 24.369511163056785
      },
      "nll": {
        "train": -5084.349189113029,
        "val": -5066.282778004509
      },
      "objective": {
        "train": -5084.349189113029,
        "val": -5066.282778004509
      }
    }
  },
  {
    "epoch": 29,
    "metrics": {
      "mse": {
        "train": 25.181573535672467,
        "val": 25.272107423241458
      },
      "nll": {
        "train": -5064.190801364272,
        "val": -5049.616167210821
      },
      "objective": {
        "train": -5064.190801364272,
        "val": -5049.616167210821
      }
    }
  },
  {
    "epoch": 30,
    "metrics": {
      "mse": {
        "train": 23.776657901593108,
        "val": 23.92831005267243
      },
      "nll": {
        "train": -5127.084356051772,
        "val": -5074.985762107432
      },
      "objective": {
        "train": -5127.084356051772,
        "val": -5074.985762107432
      }
    }
  },
  {
    "epoch": 31,
    "metrics": {
      "mse": {
        "train": 23.7812660084435,
        "val": 24.108111120575103
      },
      "nll": {
        "train": -5122.233709382774,
        "val": -5099.135710607121
      },
      "objective": {
        "train": -5122.233709382774,
        "val": -5099.135710607121
      }
    }
  },
  {
    "epoch": 32,
    "metrics": {
      "mse": {
        "train": 22.561746663715116,
        "val": 22.950921405014114
      },
      "nll": {
        "train": -5149.7086807175065,
        "val": -5122.854453319341
      },
      "objective": {
        "train": -5149.7086807175065,
        "val": -5122.854453319341
      }
    }
  },
  {
    "epoch": 33,
    "metrics": {
      "mse": {
        "train": 25.853768818414032,
        "val": 26.19813149485422
      },
      "nll": {
        "train": -5005.097583372201,
        "val": -4978.467591243004
      },
      "objective": {
        "train": -5005.097583372201,
        "val": -4978.467591243004
      }
    }
  },
  {
    "epoch": 34,
    "metrics": {
      "mse": {
        "train": 23.7534371181507,
        "val": 24.024424576640723
      },
      "nll": {
        "train": -5128.562674906716,
        "val": -5090.7741978583645
      },
      "objective": {
        "train": -5128.562674906716,
        "val": -5090.7741978583645
      }
    }
  },
  {
    "epoch": 35,
    "metrics": {
      "mse": {
        "train": 23.15893283293615,
        "val": 23.44144767552466
      },
      "nll": {
        "train": -5150.141268753887,
        "val": -5118.27003653607
      },
      "objective": {
        "train": -5150.141268753887,
        "val": -5118.27003653607
      }
    }
  },
  {
    "epoch": 36,
    "metrics": {
      "mse": {
        "train": 22.6241260642436,
        "val": 23.17067616970385
      },
      "nll": {
        "train": -5184.357023476368,
        "val": -5134.869245083178
      },
      "objective": {
        "train": -5184.357023476368,
        "val": -5134.869245083178
      }
    }
  },
  {
    "epoch": 37,
    "metrics": {
      "mse": {
        "train": 23.137557641783758,
        "val": 23.47741796958506
      },
      "nll": {
        "train": -5075.241288673818,
        "val": -5057.965295592351
      },
      "objective": {
        "train": -5075.241288673818,
        "val": -5057.965295592351
      }
    }
  },
  {
    "epoch": 38,
    "metrics": {
      "mse": {
        "train": 22.285962043116935,
        "val": 22.92404170060039
      },
      "nll": {
        "train": -5162.199199315921,
        "val": -5116.611204232742
      },
      "objective": {
        "train": -5162.199199315921,
        "val": -5116.611204232742
      }
    }
  },
  {
    "epoch": 39,
    "metrics": {
      "mse": {
        "train": 23.072854805941606,
        "val": 23.167054921240357
      },
      "nll": {
        "train": -5162.5409913324,
        "val": -5128.782850882307
      },
      "objective": {
        "train": -5162.5409913324,
        "val": -5128.782850882307
      }
    }
  },
  {
    "epoch": 40,
    "metrics": {
      "mse": {
        "train": 22.397644821091077,
        "val": 22.631165423796546
      },
      "nll": {
        "train": -5180.389667871579,
        "val": -5155.943478408738
      },
      "objective": {
        "train": -5180.389667871579,
        "val": -5155.943478408738
      }
    }
  },
  {
    "epoch": 41,
    "metrics": {
      "mse": {
        "train": 22.505146520054755,
        "val": 22.707350906447985
      },
      "nll": {
        "train": -5179.5805008162315,
        "val": -5143.539869014304
      },
      "objective": {
        "train": -5179.5805008162315,
        "val": -5143.539869014304
      }
    }
  },
  {
    "epoch": 42,
    "metrics": {
      "mse": {
        "train": 22.367209443998576,
        "val": 22.47157242997962
      },
      "nll": {
        "train": -5143.175812830379,
        "val": -5110.893972520212
      },
      "objective": {
        "train": -5143.175812830379,
        "val": -5110.893972520212
      }
    }
  },
  {
    "epoch": 43,
    "metrics": {
      "mse": {
        "train": 23.26183878960301,
        "val": 23.36252355812794
      },
      "nll": {
        "train": -5088.4988825404225,
        "val": -5066.266395075404
      },
      "objective": {
        "train": -5088.4988825404225,
        "val": -5066.266395075404
      }
    }
  },
  {
    "epoch": 44,
    "metrics": {
      "mse": {
        "train": 21.47998401300231,
        "val": 21.84491343996418
      },
      "nll": {
        "train": -5180.204648145988,
        "val": -5162.366653062811
      },
      "objective": {
        "train": -5180.204648145988,
        "val": -5162.366653062811
      }
    }
  },
  {
    "epoch": 45,
    "metrics": {
      "mse": {
        "train": 21.99126877476327,
        "val": 22.123473504289464
      },
      "nll": {
        "train": -5231.903419912158,
        "val": -5199.224966476213
      },
      "objective": {
        "train": -5231.903419912158,
        "val": -5199.224966476213
      }
    }
  },
  {
    "epoch": 46,
    "metrics": {
      "mse": {
        "train": 22.193725652362577,
        "val": 22.33370401372957
      },
      "nll": {
        "train": -5197.1882166316855,
        "val": -5167.968050373134
      },
      "objective": {
        "train": -5197.1882166316855,
        "val": -5167.968050373134
      }
    }
  },
  {
    "epoch": 47,
    "metrics": {
      "mse": {
        "train": 21.98795983328748,
        "val": 22.304409449373313
      },
      "nll": {
        "train": -5240.640416083645,
        "val": -5197.003267354633
      },
      "objective": {
        "train": -5240.640416083645,
        "val": -5197.003267354633
      }
    }
  }
]