[
  {
    "epoch": 0,
    "metrics": {
      "cross_entropy": {
        "train": 2.314387071648244,
        "val": 2.31714474583024
      },
      "accuracy": {
        "train": 0.07817278454522084,
        "val": 0.07591482328175399
      }
    }
  },
  {
    "epoch": 1,
    "metrics": {
      "cross_entropy": {
        "train": 1.8701749764294955,
        "val": 1.8804225245305093
      },
      "accuracy": {
        "train": 0.29789210157407886,
        "val": 0.3007380161881172
      }
    }
  },
  {
    "epoch": 2,
    "metrics": {
      "cross_entropy": {
        "train": 1.777808493117986,
        "val": 1.7750601165848905
      },
      "accuracy": {
        "train": 0.32021353027000926,
        "val": 0.32787516309683834
      }
    }
  },
  {
    "epoch": 3,
    "metrics": {
      "cross_entropy": {
        "train": 1.7201156952121779,
        "val": 1.7384673772702797
      },
      "accuracy": {
        "train": 0.359600272089448,
        "val": 0.36888838599941165
      }
    }
  },
  {
    "epoch": 4,
    "metrics": {
      "cross_entropy": {
        "train": 1.684227515485621,
        "val": 1.7122853155285669
      },
      "accuracy": {
        "train": 0.3558595556653499,
        "val": 0.35585794355239153
      }
    }
  },
  {
    "epoch": 5,
    "metrics": {
      "cross_entropy": {
        "train": 1.651400987356706,
        "val": 1.685513980164299
      },
      "accuracy": {
        "train": 0.36334098870640186,
        "val": 0.36469865742232305
      }
    }
  },
  {
    "epoch": 6,
    "metrics": {
      "cross_entropy": {
        "train": 1.4414542597251045,
        "val": 1.4968113939370615
      },
      "accuracy": {
        "train": 0.45295435925494015,
        "val": 0.44899293959030806
      }
    }
  },
  {
    "epoch": 7,
    "metrics": {
      "cross_entropy": {
        "train": 1.3011751622547485,
        "val": 1.355054634413596
      },
      "accuracy": {
        "train": 0.5182530733648087,
        "val": 0.5141835939895183
      }
    }
  },
  {
    "epoch": 8,
    "metrics": {
      "cross_entropy": {
        "train": 1.2553810930150522,
        "val": 1.3256863476605434
      },
      "accuracy": {
        "train": 0.5343763811579695,
        "val": 0.52444650997095
      }
    }
  },
  {
    "epoch": 9,
    "metrics": {
      "cross_entropy": {
        "train": 1.1824000219510549,
        "val": 1.274475704919808
      },
      "accuracy": {
        "train": 0.5678380467046448,
        "val": 0.5487392531824727
      }
    }
  },
  {
    "epoch": 10,
    "metrics": {
      "cross_entropy": {
        "train": 1.2491496465856096,
        "val": 1.3292285622375917
      },
      "accuracy": {
        "train": 0.5487522003369047,
        "val": 0.5260224630609429
      }
    }
  },
  {
    "epoch": 11,
    "metrics": {
      "cross_entropy": {
        "train": 1.1504849179368344,
        "val": 1.2267797265435496
      },
      "accuracy": {
        "train": 0.5750873914747688,
        "val": 0.5630381460476845
      }
    }
  },
  {
    "epoch": 12,
    "metrics": {
      "cross_entropy": {
        "train": 1.1333183727543288,
        "val": 1.2040923649094641
      },
      "accuracy": {
        "train": 0.5948558493784653,
        "val": 0.5810655158329274
      }
    }
  },
  {
    "epoch": 13,
    "metrics": {
      "cross_entropy": {
        "train": 0.9777286824517606,
        "val": 1.085829423554929
      },
      "accuracy": {
        "train": 0.6639908450224765,
        "val": 0.6333794776364007
      }
    }
  },
  {
    "epoch": 14,
    "metrics": {
      "cross_entropy": {
        "train": 0.9462832523458594,
        "val": 1.096185658388252
      },
      "accuracy": {
        "train": 0.6773837015892075,
        "val": 0.6313807073829358
      }
    }
  },
  {
    "epoch": 15,
    "metrics": {
      "cross_entropy": {
        "train": 0.8825122568253452,
        "val": 1.009037522537242
      },
      "accuracy": {
        "train": 0.6919916096103145,
        "val": 0.6628613348816593
      }
    }
  },
  {
    "epoch": 16,
    "metrics": {
      "cross_entropy": {
        "train": 0.8709800291225451,
        "val": 1.0290972532436418
      },
      "accuracy": {
        "train": 0.6983672103809185,
        "val": 0.661631322572372
      }
    }
  },
  {
    "epoch": 17,
    "metrics": {
      "cross_entropy": {
        "train": 0.8257576316780609,
        "val": 0.9548379890208315
      },
      "accuracy": {
        "train": 0.7149683462839139,
        "val": 0.6813115194109973
      }
    }
  },
  {
    "epoch": 18,
    "metrics": {
      "cross_entropy": {
        "train": 0.8254447784738647,
        "val": 0.9585383749701
      },
      "accuracy": {
        "train": 0.7163062660636315,
        "val": 0.6806580768795031
      }
    }
  },
  {
    "epoch": 19,
    "metrics": {
      "cross_entropy": {
        "train": 0.8200883348893525,
        "val": 0.9596617633676177
      },
      "accuracy": {
        "train": 0.7140263409242718,
        "val": 0.6786977439513946
      }
    }
  },
  {
    "epoch": 20,
    "metrics": {
      "cross_entropy": {
        "train": 0.8328013029510978,
        "val": 0.9793859653972172
      },
      "accuracy": {
        "train": 0.7073640434820874,
        "val": 0.6718942380039454
      }
    }
  },
  {
    "epoch": 21,
    "metrics": {
      "cross_entropy": {
        "train": 0.7834130817826539,
        "val": 0.9361831788867162
      },
      "accuracy": {
        "train": 0.7328937513702506,
        "val": 0.6913053696060972
      }
    }
  },
  {
    "epoch": 22,
    "metrics": {
      "cross_entropy": {
        "train": 0.7644108308974756,
        "val": 0.9195296693304588
      },
      "accuracy": {
        "train": 0.7345183687003849,
        "val": 0.6931119513082769
      }
    }
  },
  {
    "epoch": 23,
    "metrics": {
      "cross_entropy": {
        "train": 0.7547609841165427,
        "val": 0.9019248050077375
      },
      "accuracy": {
        "train": 0.743665375791949,
        "val": 0.7034517410331547
      }
    }
  },
  {
    "epoch": 24,
    "metrics": {
      "cross_entropy": {
        "train": 0.7529757276841416,
        "val": 0.9130298656401159
      },
      "accuracy": {
        "train": 0.7435698099287903,
        "val": 0.7048355054756372
      }
    }
  },
  {
    "epoch": 25,
    "metrics": {
      "cross_entropy": {
        "train": 0.7409580671820463,
        "val": 0.9260905849097839
      },
      "accuracy": {
        "train": 0.7472422653479626,
        "val": 0.699492638978791
      }
    }
  },
  {
    "epoch": 26,
    "metrics": {
      "cross_entropy": {
        "train": 0.7557758468680503,
        "val": 0.9413746853266255
      },
      "accuracy": {
        "train": 0.7384911728424763,
        "val": 0.6908825530337231
      }
    }
  },
  {
    "epoch": 27,
    "metrics": {
      "cross_entropy": {
        "train": 0.745238618673769,
        "val": 0.9158510070335382
      },
      "accuracy": {
        "train": 0.74422511843132,
        "val": 0.7015298471624561
      }
    }
  },
  {
    "epoch": 28,
    "metrics": {
      "cross_entropy": {
        "train": 0.7457841351618538,
        "val": 0.9242232613595429
      },
      "accuracy": {
        "train": 0.7426278043738511,
        "val": 0.6954566616688708
      }
    }
  },
  {
    "epoch": 29,
    "metrics": {
      "cross_entropy": {
        "train": 0.7123193643489172,
        "val": 0.8929356423746175
      },
      "accuracy": {
        "train": 0.7552288316121889,
        "val": 0.7035286172784563
      }
    }
  },
  {
    "epoch": 30,
    "metrics": {
      "cross_entropy": {
        "train": 0.70576184213181,
        "val": 0.889827848319308
      },
      "accuracy": {
        "train": 0.7598979008990691,
        "val": 0.7102168096552476
      }
    }
  },
  {
    "epoch": 31,
    "metrics": {
      "cross_entropy": {
        "train": 0.7083158027600414,
        "val": 0.918634798281527
      },
      "accuracy": {
        "train": 0.7570445802975764,
        "val": 0.6984548165954347
      }
    }
  },
  {
    "epoch": 32,
    "metrics": {
      "cross_entropy": {
        "train": 0.7230142630407218,
        "val": 0.9103253634983323
      },
      "accuracy": {
        "train": 0.7483480979211209,
        "val": 0.6984932544981421
      }
    }
  },
  {
    "epoch": 33,
    "metrics": {
      "cross_entropy": {
        "train": 0.7245491667410181,
        "val": 0.9206380939791563
      },
      "accuracy": {
        "train": 0.751078547717,
        "val": 0.6997617044627007
      }
    }
  },
  {
    "epoch": 34,
    "metrics": {
      "cross_entropy": {
        "train": 0.7238076427612127,
        "val": 0.9304235082160943
      },
      "accuracy": {
        "train": 0.7525666422975954,
        "val": 0.6943035255498992
      }
    }
  },
  {
    "epoch": 35,
    "metrics": {
      "cross_entropy": {
        "train": 0.7251342361155766,
        "val": 0.933641426512676
      },
      "accuracy": {
        "train": 0.7495904523552167,
        "val": 0.6939575840131383
      }
    }
  },
  {
    "epoch": 36,
    "metrics": {
      "cross_entropy": {
        "train": 0.7066326558731526,
        "val": 0.9158786652520354
      },
      "accuracy": {
        "train": 0.7583961537105384,
        "val": 0.7037208062146423
      }
    }
  },
  {
    "epoch": 37,
    "metrics": {
      "cross_entropy": {
        "train": 0.6923203406413605,
        "val": 0.8852800378005443
      },
      "accuracy": {
        "train": 0.7656728029055802,
        "val": 0.7163284328865829
      }
    }
  },
  {
    "epoch": 38,
    "metrics": {
      "cross_entropy": {
        "train": 0.6793551602123762,
        "val": 0.8965291742276662
      },
      "accuracy": {
        "train": 0.7681575119690689,
        "val": 0.7096018029919849
      }
    }
  },
  {
    "epoch": 39,
    "metrics": {
      "cross_entropy": {
        "train": 0.6729513209210624,
        "val": 0.8662819444885773
      },
      "accuracy": {
        "train": 0.7674475953295378,
        "val": 0.7181350134615528
      }
    }
  },
  {
    "epoch": 40,
    "metrics": {
      "cross_entropy": {
        "train": 0.6760518775317882,
        "val": 0.899322185184243
      },
      "accuracy": {
        "train": 0.7691814309745285,
        "val": 0.7058733274191068
      }
    }
  },
  {
    "epoch": 41,
    "metrics": {
      "cross_entropy": {
        "train": 0.6606569793587977,
        "val": 0.8805004318426896
      },
      "accuracy": {
        "train": 0.7738095437363278,
        "val": 0.718673143522106
      }
    }
  },
  {
    "epoch": 42,
    "metrics": {
      "cross_entropy": {
        "train": 0.6774649739065263,
        "val": 0.8979283989548024
      },
      "accuracy": {
        "train": 0.7705466555892875,
        "val": 0.7230550625612375
      }
    }
  },
  {
    "epoch": 43,
    "metrics": {
      "cross_entropy": {
        "train": 0.6652417744352418,
        "val": 0.8967280304987272
      },
      "accuracy": {
        "train": 0.7702190019727378,
        "val": 0.7152521727104908
      }
    }
  },
  {
    "epoch": 44,
    "metrics": {
      "cross_entropy": {
        "train": 0.6461439216179897,
        "val": 0.8575907179680258
      },
      "accuracy": {
        "train": 0.7791066160852756,
        "val": 0.7272447922792822
      }
    }
  },
  {
    "epoch": 45,
    "metrics": {
      "cross_entropy": {
        "train": 0.646125426127784,
        "val": 0.8702694566927273
      },
      "accuracy": {
        "train": 0.7775502598711422,
        "val": 0.7207487899383935
      }
    }
  },
  {
    "epoch": 46,
    "metrics": {
      "cross_entropy": {
        "train": 0.6437820411369028,
        "val": 0.8797263026484924
      },
      "accuracy": {
        "train": 0.7772635630433243,
        "val": 0.7124077687074337
      }
    }
  },
  {
    "epoch": 47,
    "metrics": {
      "cross_entropy": {
        "train": 0.6530358565392688,
        "val": 0.8834309218334536
      },
      "accuracy": {
        "train": 0.7764990369192426,
        "val": 0.7160209296924162
      }
    }
  },
  {
    "epoch": 48,
    "metrics": {
      "cross_entropy": {
        "train": 0.6485748150035602,
        "val": 0.889314889880344
      },
      "accuracy": {
        "train": 0.7749836375329003,
        "val": 0.7121387027011586
      }
    }
  },
  {
    "epoch": 49,
    "metrics": {
      "cross_entropy": {
        "train": 0.6345133391327346,
        "val": 0.8851288527772655
      },
      "accuracy": {
        "train": 0.7811408018104996,
        "val": 0.7145218517067687
      }
    }
  },
  {
    "epoch": 50,
    "metrics": {
      "cross_entropy": {
        "train": 0.6591745212888968,
        "val": 0.91012012580499
      },
      "accuracy": {
        "train": 0.7749563324537377,
        "val": 0.7107933771511286
      }
    }
  }
]